{
  "acceptedNameList": {
    "acceptedNames": [null],
    "class": "gov.usgs.itis.itis_service.data.SvcAcceptedNameList",
    "tsn": "180092"
  },
  "class": "gov.usgs.itis.itis_service.data.SvcFullRecord",
  "commentList": {
    "class": "gov.usgs.itis.itis_service.data.SvcTaxonCommentList",
    "comments": [
      {
        "class": "gov.usgs.itis.itis_service.data.SvcTaxonComment",
        "commentDetail": "Comments:  Most of the synonyms have fossil specimens as their type specimens; Bory de St. Vincent's names refer to living geographic varieties of modern humans",
        "commentId": "27932",
        "commentTimeStamp": "2014-06-26 23:03:49.0",
        "commentator": "Wilson & Reeder, eds. (2005)",
        "updateDate": "2017-03-30"
      },
      {
        "class": "gov.usgs.itis.itis_service.data.SvcTaxonComment",
        "commentDetail": "Status:  CITES - Appendix II as Order Primates; absolutely not endangered",
        "commentId": "27933",
        "commentTimeStamp": "2014-06-26 23:03:49.0",
        "commentator": "Wilson & Reeder, eds. (2005)",
        "updateDate": "2017-03-30"
      }
    ],
    "tsn": "180092"
  },
  "commonNameList": {
    "class": "gov.usgs.itis.itis_service.data.SvcCommonNameList",
    "commonNames": [
      {
        "class": "gov.usgs.itis.itis_service.data.SvcCommonName",
        "commonName": "man",
        "language": "English",
        "tsn": "180092"
      },
      {
        "class": "gov.usgs.itis.itis_service.data.SvcCommonName",
        "commonName": "Humans",
        "language": "English",
        "tsn": "180092"
      },
      {
        "class": "gov.usgs.itis.itis_service.data.SvcCommonName",
        "commonName": "Human",
        "language": "English",
        "tsn": "180092"
      }
    ],
    "tsn": "180092"
  },
  "completenessRating": {
    "class": "gov.usgs.itis.itis_service.data.SvcGlobalSpeciesCompleteness",
    "completeness": "",
    "rankId": 220,
    "tsn": "180092"
  },
  "coreMetadata": {
    "class": "gov.usgs.itis.itis_service.data.SvcCoreMetadata",
    "credRating": "TWG standards met",
    "rankId": 220,
    "taxonCoverage": "",
    "taxonCurrency": "",
    "taxonUsageRating": "valid",
    "tsn": "180092",
    "unacceptReason": ""
  },
  "credibilityRating": {
    "class": "gov.usgs.itis.itis_service.data.SvcCredibilityData",
    "credRating": "TWG standards met",
    "tsn": "180092"
  },
  "currencyRating": {
    "class": "gov.usgs.itis.itis_service.data.SvcCurrencyData",
    "rankId": 220,
    "taxonCurrency": "",
    "tsn": "180092"
  },
  "dateData": {
    "class": "gov.usgs.itis.itis_service.data.SvcTaxonDateData",
    "initialTimeStamp": "1996-06-13 14:51:08.0",
    "tsn": "180092",
    "updateDate": "2017-03-30"
  },
  "expertList": {
    "class": "gov.usgs.itis.itis_service.data.SvcTaxonExpertList",
    "experts": [
      {
        "class": "gov.usgs.itis.itis_service.data.SvcTaxonExpert",
        "comment": "Curator of North American mammals and Chief of Mammal Section, National Biological Service, Smithsonian Institution, National Museum of Natural History, Washington, DC, USA",
        "expert": "Alfred L. Gardner",
        "referenceFor": [
          {
            "class": "gov.usgs.itis.itis_service.data.SvcReferenceForElement",
            "name": "Homo sapiens",
            "refLanguage": null,
            "referredTsn": "180092"
          }
        ],
        "updateDate": "2003-10-28"
      },
      {
        "class": "gov.usgs.itis.itis_service.data.SvcTaxonExpert",
        "comment": "Deputy Chair, IUCN SSC Primate Specialist Group, Office of the Executive Vice Chair, Conservation International, 2011 Crystal Drive, Arlington, Virginia 22202, USA",
        "expert": "Anthony B. Rylands",
        "referenceFor": [
          {
            "class": "gov.usgs.itis.itis_service.data.SvcReferenceForElement",
            "name": "Homo sapiens",
            "refLanguage": null,
            "referredTsn": "180092"
          }
        ],
        "updateDate": "2017-03-30"
      },
      {
        "class": "gov.usgs.itis.itis_service.data.SvcTaxonExpert",
        "comment": "Department of Archaeology and Anthropology, The Australian National University, GPO Box 4, Canberra ACT 0200, Australia",
        "expert": "Colin P. Groves",
        "referenceFor": [
          {
            "class": "gov.usgs.itis.itis_service.data.SvcReferenceForElement",
            "name": "Homo sapiens",
            "refLanguage": null,
            "referredTsn": "180092"
          }
        ],
        "updateDate": "2002-07-30"
      }
    ],
    "tsn": "180092"
  },
  "geographicDivisionList": {
    "class": "gov.usgs.itis.itis_service.data.SvcTaxonGeoDivisionList",
    "geoDivisions": [
      {
        "class": "gov.usgs.itis.itis_service.data.SvcTaxonGeoDivision",
        "geographicValue": "Africa",
        "updateDate": "2002-07-30"
      },
      {
        "class": "gov.usgs.itis.itis_service.data.SvcTaxonGeoDivision",
        "geographicValue": "Australia",
        "updateDate": "2002-07-30"
      },
      {
        "class": "gov.usgs.itis.itis_service.data.SvcTaxonGeoDivision",
        "geographicValue": "Caribbean",
        "updateDate": "2002-07-30"
      },
      {
        "class": "gov.usgs.itis.itis_service.data.SvcTaxonGeoDivision",
        "geographicValue": "Europe & Northern Asia (excluding China)",
        "updateDate": "2002-07-30"
      },
      {
        "class": "gov.usgs.itis.itis_service.data.SvcTaxonGeoDivision",
        "geographicValue": "Middle America",
        "updateDate": "2002-07-30"
      },
      {
        "class": "gov.usgs.itis.itis_service.data.SvcTaxonGeoDivision",
        "geographicValue": "North America",
        "updateDate": "2002-07-30"
      },
      {
        "class": "gov.usgs.itis.itis_service.data.SvcTaxonGeoDivision",
        "geographicValue": "Oceania",
        "updateDate": "2002-07-30"
      },
      {
        "class": "gov.usgs.itis.itis_service.data.SvcTaxonGeoDivision",
        "geographicValue": "South America",
        "updateDate": "2002-07-30"
      },
      {
        "class": "gov.usgs.itis.itis_service.data.SvcTaxonGeoDivision",
        "geographicValue": "Southern Asia",
        "updateDate": "2002-07-30"
      }
    ],
    "tsn": "180092"
  },
  "hierarchyUp": {
    "author": null,
    "class": "gov.usgs.itis.itis_service.data.SvcHierarchyRecord",
    "parentName": "Homo",
    "parentTsn": "180091",
    "rankName": "Species",
    "taxonName": "Homo sapiens",
    "tsn": "180092"
  },
  "jurisdictionalOriginList": {
    "class": "gov.usgs.itis.itis_service.data.SvcTaxonJurisdictionalOriginList",
    "jurisdictionalOrigins": [
      {
        "class": "gov.usgs.itis.itis_service.data.SvcTaxonJurisdictionalOrigin",
        "jurisdictionValue": "Alaska",
        "origin": "Native",
        "updateDate": "2014-06-26"
      },
      {
        "class": "gov.usgs.itis.itis_service.data.SvcTaxonJurisdictionalOrigin",
        "jurisdictionValue": "Canada",
        "origin": "Native",
        "updateDate": "2014-06-26"
      },
      {
        "class": "gov.usgs.itis.itis_service.data.SvcTaxonJurisdictionalOrigin",
        "jurisdictionValue": "Caribbean Territories",
        "origin": "Native",
        "updateDate": "2014-06-26"
      },
      {
        "class": "gov.usgs.itis.itis_service.data.SvcTaxonJurisdictionalOrigin",
        "jurisdictionValue": "Central Pacific Territories",
        "origin": "Native",
        "updateDate": "2014-06-26"
      },
      {
        "class": "gov.usgs.itis.itis_service.data.SvcTaxonJurisdictionalOrigin",
        "jurisdictionValue": "Continental US",
        "origin": "Native",
        "updateDate": "2014-06-26"
      },
      {
        "class": "gov.usgs.itis.itis_service.data.SvcTaxonJurisdictionalOrigin",
        "jurisdictionValue": "Hawaii",
        "origin": "Native",
        "updateDate": "2014-06-26"
      },
      {
        "class": "gov.usgs.itis.itis_service.data.SvcTaxonJurisdictionalOrigin",
        "jurisdictionValue": "Mexico",
        "origin": "Native",
        "updateDate": "2014-06-26"
      }
    ],
    "tsn": "180092"
  },
  "kingdom": {
    "class": "gov.usgs.itis.itis_service.data.SvcKingdomInfo",
    "kingdomId": "5",
    "kingdomName": "Animalia  ",
    "tsn": "180092"
  },
  "otherSourceList": {
    "class": "gov.usgs.itis.itis_service.data.SvcTaxonOtherSourceList",
    "otherSources": [
      {
        "acquisitionDate": "1996-07-29",
        "class": "gov.usgs.itis.itis_service.data.SvcTaxonOtherSource",
        "referenceFor": [
          {
            "class": "gov.usgs.itis.itis_service.data.SvcReferenceForElement",
            "name": "Homo sapiens",
            "refLanguage": null,
            "referredTsn": "180092"
          }
        ],
        "source": "NODC Taxonomic Code",
        "sourceComment": "",
        "sourceType": "database",
        "updateDate": "2010-01-14",
        "version": "8.0"
      }
    ],
    "tsn": "180092"
  },
  "parentTSN": {
    "class": "gov.usgs.itis.itis_service.data.SvcParentTsn",
    "parentTsn": "180091",
    "tsn": "180092"
  },
  "publicationList": {
    "class": "gov.usgs.itis.itis_service.data.SvcTaxonPublicationList",
    "publications": [
      {
        "actualPubDate": "1987-01-01",
        "class": "gov.usgs.itis.itis_service.data.SvcTaxonPublication",
        "isbn": "",
        "issn": "",
        "listedPubDate": "1987-01-01",
        "pages": "79",
        "pubComment": "",
        "pubName": "Resource Publication, no. 166",
        "pubPlace": "Washington, D.C., USA",
        "publisher": "United States Department of the Interior Fish and Wildlife Service",
        "referenceAuthor": "Banks, R. C., R. W. McDiarmid, and A. L. Gardner",
        "referenceFor": [
          {
            "class": "gov.usgs.itis.itis_service.data.SvcReferenceForElement",
            "name": "Homo sapiens",
            "refLanguage": null,
            "referredTsn": "180092"
          }
        ],
        "title": "Checklist of Vertebrates of the United States, the U.S. Territories, and Canada",
        "updateDate": "2019-11-04"
      },
      {
        "actualPubDate": "1993-01-01",
        "class": "gov.usgs.itis.itis_service.data.SvcTaxonPublication",
        "isbn": "1-56098-217-9",
        "issn": "",
        "listedPubDate": "1992-01-01",
        "pages": "xviii + 1207",
        "pubComment": "Corrections were made to text at 3rd printing",
        "pubName": "Mammal Species of the World: A Taxonomic and Geographic Reference, 2nd ed., 3rd printing",
        "pubPlace": "Washington, DC, USA",
        "publisher": "Smithsonian Institution Press",
        "referenceAuthor": "Wilson, Don E., and DeeAnn M. Reeder, eds.",
        "referenceFor": [
          {
            "class": "gov.usgs.itis.itis_service.data.SvcReferenceForElement",
            "name": "Homo sapiens",
            "refLanguage": null,
            "referredTsn": "180092"
          }
        ],
        "title": "",
        "updateDate": "2019-11-04"
      },
      {
        "actualPubDate": "2005-10-01",
        "class": "gov.usgs.itis.itis_service.data.SvcTaxonPublication",
        "isbn": "0-8018-8221-4",
        "issn": "",
        "listedPubDate": "2005-10-01",
        "pages": "xxxv + 743",
        "pubComment": "",
        "pubName": "Mammal Species of the World: A Taxonomic and Geographic Reference, 3rd ed., vol. 1",
        "pubPlace": "Baltimore, Maryland, USA",
        "publisher": "Johns Hopkins University Press",
        "referenceAuthor": "Wilson, Don E., and DeeAnn M. Reeder, eds.",
        "referenceFor": [
          {
            "class": "gov.usgs.itis.itis_service.data.SvcReferenceForElement",
            "name": "Homo sapiens",
            "refLanguage": null,
            "referredTsn": "180092"
          },
          {
            "class": "gov.usgs.itis.itis_service.data.SvcReferenceForElement",
            "name": "Human",
            "refLanguage": "English",
            "referredTsn": "180092"
          }
        ],
        "title": "",
        "updateDate": "2018-01-26"
      },
      {
        "actualPubDate": "2000-01-01",
        "class": "gov.usgs.itis.itis_service.data.SvcTaxonPublication",
        "isbn": "1-56098-383-3",
        "issn": "",
        "listedPubDate": "2000-01-01",
        "pages": "xiv + 204",
        "pubComment": "With contributions by Bernadette N. Graham, Adam P. Potter, and Mariana M. Upmeyer",
        "pubName": "Common Names of Mammals of the World",
        "pubPlace": "Washington, DC, USA",
        "publisher": "Smithsonian Institution Press",
        "referenceAuthor": "Wilson, Don E., and F. Russell Cole",
        "referenceFor": [
          {
            "class": "gov.usgs.itis.itis_service.data.SvcReferenceForElement",
            "name": "Homo sapiens",
            "refLanguage": null,
            "referredTsn": "180092"
          }
        ],
        "title": "",
        "updateDate": "2019-11-04"
      }
    ],
    "tsn": "180092"
  },
  "scientificName": {
    "author": "Linnaeus, 1758",
    "class": "gov.usgs.itis.itis_service.data.SvcScientificName",
    "combinedName": "Homo sapiens",
    "kingdom": null,
    "tsn": "180092",
    "unitInd1": null,
    "unitInd2": null,
    "unitInd3": null,
    "unitInd4": null,
    "unitName1": "Homo                               ",
    "unitName2": "sapiens",
    "unitName3": null,
    "unitName4": null
  },
  "synonymList": {
    "class": "gov.usgs.itis.itis_service.data.SvcSynonymNameList",
    "synonyms": [
      {
        "author": null,
        "class": "gov.usgs.itis.itis_service.data.SvcTaxonName",
        "sciName": "Homo aethiopicus",
        "tsn": "944513"
      },
      {
        "author": null,
        "class": "gov.usgs.itis.itis_service.data.SvcTaxonName",
        "sciName": "Homo americanus",
        "tsn": "944514"
      },
      {
        "author": null,
        "class": "gov.usgs.itis.itis_service.data.SvcTaxonName",
        "sciName": "Homo arabicus",
        "tsn": "944515"
      },
      {
        "author": null,
        "class": "gov.usgs.itis.itis_service.data.SvcTaxonName",
        "sciName": "Homo australasicus",
        "tsn": "944516"
      },
      {
        "author": null,
        "class": "gov.usgs.itis.itis_service.data.SvcTaxonName",
        "sciName": "Homo cafer",
        "tsn": "944517"
      },
      {
        "author": null,
        "class": "gov.usgs.itis.itis_service.data.SvcTaxonName",
        "sciName": "Homo capensis",
        "tsn": "944518"
      },
      {
        "author": null,
        "class": "gov.usgs.itis.itis_service.data.SvcTaxonName",
        "sciName": "Homo columbicus",
        "tsn": "944519"
      },
      {
        "author": null,
        "class": "gov.usgs.itis.itis_service.data.SvcTaxonName",
        "sciName": "Homo drennani",
        "tsn": "944520"
      },
      {
        "author": null,
        "class": "gov.usgs.itis.itis_service.data.SvcTaxonName",
        "sciName": "Homo grimaldii",
        "tsn": "944521"
      },
      {
        "author": null,
        "class": "gov.usgs.itis.itis_service.data.SvcTaxonName",
        "sciName": "Homo hottentotus",
        "tsn": "944522"
      },
      {
        "author": null,
        "class": "gov.usgs.itis.itis_service.data.SvcTaxonName",
        "sciName": "Homo hyperboreus",
        "tsn": "944523"
      },
      {
        "author": null,
        "class": "gov.usgs.itis.itis_service.data.SvcTaxonName",
        "sciName": "Homo indicus",
        "tsn": "944524"
      },
      {
        "author": null,
        "class": "gov.usgs.itis.itis_service.data.SvcTaxonName",
        "sciName": "Homo japeticus",
        "tsn": "944525"
      },
      {
        "author": null,
        "class": "gov.usgs.itis.itis_service.data.SvcTaxonName",
        "sciName": "Homo melaninus",
        "tsn": "944526"
      },
      {
        "author": null,
        "class": "gov.usgs.itis.itis_service.data.SvcTaxonName",
        "sciName": "Homo monstrosus",
        "tsn": "944527"
      },
      {
        "author": null,
        "class": "gov.usgs.itis.itis_service.data.SvcTaxonName",
        "sciName": "Homo neptunianus",
        "tsn": "944528"
      },
      {
        "author": null,
        "class": "gov.usgs.itis.itis_service.data.SvcTaxonName",
        "sciName": "Homo palestinus",
        "tsn": "944529"
      },
      {
        "author": null,
        "class": "gov.usgs.itis.itis_service.data.SvcTaxonName",
        "sciName": "Homo patagonus",
        "tsn": "944530"
      },
      {
        "author": null,
        "class": "gov.usgs.itis.itis_service.data.SvcTaxonName",
        "sciName": "Homo priscus",
        "tsn": "944531"
      },
      {
        "author": null,
        "class": "gov.usgs.itis.itis_service.data.SvcTaxonName",
        "sciName": "Homo scythicus",
        "tsn": "944532"
      },
      {
        "author": null,
        "class": "gov.usgs.itis.itis_service.data.SvcTaxonName",
        "sciName": "Homo sinicus",
        "tsn": "944533"
      },
      {
        "author": null,
        "class": "gov.usgs.itis.itis_service.data.SvcTaxonName",
        "sciName": "Homo spelaeus",
        "tsn": "944534"
      },
      {
        "author": null,
        "class": "gov.usgs.itis.itis_service.data.SvcTaxonName",
        "sciName": "Homo troglodytes",
        "tsn": "944535"
      },
      {
        "author": null,
        "class": "gov.usgs.itis.itis_service.data.SvcTaxonName",
        "sciName": "Homo wadjakensis",
        "tsn": "944536"
      },
      {
        "author": null,
        "class": "gov.usgs.itis.itis_service.data.SvcTaxonName",
        "sciName": "Homo sapiens cro-magnonensis",
        "tsn": "945628"
      },
      {
        "author": null,
        "class": "gov.usgs.itis.itis_service.data.SvcTaxonName",
        "sciName": "Homo sapiens grimaldiensis",
        "tsn": "945629"
      },
      {
        "author": null,
        "class": "gov.usgs.itis.itis_service.data.SvcTaxonName",
        "sciName": "Homo fossilis proto-aethiopicus",
        "tsn": "945630"
      },
      {
        "author": null,
        "class": "gov.usgs.itis.itis_service.data.SvcTaxonName",
        "sciName": "Homo fossilis protoaethiopicus",
        "tsn": "945728"
      },
      {
        "author": null,
        "class": "gov.usgs.itis.itis_service.data.SvcTaxonName",
        "sciName": "Homo sapiens cromagnonensis",
        "tsn": "945730"
      }
    ],
    "tsn": "180092"
  },
  "taxRank": {
    "class": "gov.usgs.itis.itis_service.data.SvcTaxonRankInfo",
    "kingdomId": "5",
    "kingdomName": "Animalia  ",
    "rankId": "220",
    "rankName": "Species        ",
    "tsn": "180092"
  },
  "taxonAuthor": {
    "authorship": "Linnaeus, 1758",
    "class": "gov.usgs.itis.itis_service.data.SvcTaxonAuthorship",
    "tsn": "180092",
    "updateDate": "2004-04-09"
  },
  "tsn": "180092",
  "unacceptReason": {
    "class": "gov.usgs.itis.itis_service.data.SvcUnacceptData",
    "tsn": "180092",
    "unacceptReason": null
  },
  "usage": {
    "class": "gov.usgs.itis.itis_service.data.SvcTaxonUsageData",
    "taxonUsageRating": "valid",
    "tsn": "180092"
  }
}
